<?xml version="1.0"?>
<form id="unnamed"><fields><field id="field0" is_required="0"><type>string</type><value></value><length>3-10</length><title><en>&#x417;&#x430;&#x433;&#x43E;&#x43B;&#x43E;&#x432;&#x43E;&#x43A;</en></title></field><field id="currency_id" is_required="0"><type>list</type><value></value><title><en>&#x412;&#x430;&#x43B;&#x44E;&#x442;&#x430;</en></title><list not_null="1"><key_title>currency_id</key_title><value_title>cur_title_ru</value_title></list></field><field id="purpose_id" is_required="0"><type>list</type><value></value><title><en>&#x41D;&#x430;&#x437;&#x43D;&#x430;&#x447;&#x435;&#x43D;&#x438;&#x435;</en></title><list not_null="1"><key_title>purpose_id</key_title><value_title>purpose_title_ru</value_title></list></field></fields></form>
